grabpy/__init__.py
grabpy/exception.py
grabpy/io.py
grabpy/request.py
grabpy/robots.py
grabpy/scraper.py
grabpy-0.1.3.dist-info/licenses/LICENCE
grabpy-0.1.3.dist-info/METADATA
grabpy-0.1.3.dist-info/WHEEL
grabpy-0.1.3.dist-info/top_level.txt
grabpy-0.1.3.dist-info/RECORD
