Metadata-Version: 2.4
Name: grabpy
Version: 0.1.3
Summary: Simple package for requesting web pages that respects robots.txt
Author-email: Riain Ó Tuathail <rotuathail01@gmail.com>
License-Expression: MIT
Project-URL: Homepage, https://github.com/belfastkeyboard/grabpy
Project-URL: Issues, https://github.com/belfastkeyboard/grabpy/issues
Classifier: Programming Language :: Python :: 3
Classifier: Operating System :: OS Independent
Requires-Python: >=3.9
License-File: LICENCE
Requires-Dist: requests==2.32.5
Dynamic: license-file
